grable/__init__.py
grable-0.0.1.dist-info/LICENSE
grable-0.0.1.dist-info/METADATA
grable-0.0.1.dist-info/WHEEL
grable-0.0.1.dist-info/top_level.txt
grable-0.0.1.dist-info/RECORD
