Metadata-Version: 2.1
Name: grable
Version: 0.0.1
Summary: An interpreter for a simple tabular language for grammatical description
Home-page: https://github.com/littell/grable
Author: Patrick Littell
Author-email: Patrick.Littell@nrc-cnrc.gc.ca
License: UNKNOWN
Platform: UNKNOWN
Classifier: Programming Language :: Python :: 3
Classifier: License :: OSI Approved :: MIT License
Classifier: Operating System :: OS Independent
Requires-Python: >=3.6
